umap/__init__.py
umap/aligned_umap.py
umap/distances.py
umap/layouts.py
umap/parametric_umap.py
umap/plot.py
umap/sparse.py
umap/spectral.py
umap/umap_.py
umap/utils.py
umap/validation.py
umap_learn_no_tf-0.5.7.dist-info/LICENSE.txt
umap_learn_no_tf-0.5.7.dist-info/METADATA
umap_learn_no_tf-0.5.7.dist-info/WHEEL
umap_learn_no_tf-0.5.7.dist-info/top_level.txt
umap_learn_no_tf-0.5.7.dist-info/RECORD
