Metadata-Version: 2.1
Name: umap-learn-no-tf
Version: 0.5.7
Summary: Uniform Manifold Approximation and Projection
Home-page: http://github.com/lmcinnes/umap
Maintainer: Leland McInnes
Maintainer-email: leland.mcinnes@gmail.com
License: BSD
Keywords: dimension reduction t-sne manifold
Classifier: Development Status :: 3 - Alpha
Classifier: Intended Audience :: Science/Research
Classifier: Intended Audience :: Developers
Classifier: License :: OSI Approved
Classifier: Programming Language :: C
Classifier: Programming Language :: Python
Classifier: Topic :: Software Development
Classifier: Topic :: Scientific/Engineering
Classifier: Operating System :: Microsoft :: Windows
Classifier: Operating System :: POSIX
Classifier: Operating System :: Unix
Classifier: Operating System :: MacOS
Classifier: Programming Language :: Python :: 3.9
Classifier: Programming Language :: Python :: 3.10
Classifier: Programming Language :: Python :: 3.11
Classifier: Programming Language :: Python :: 3.12
License-File: LICENSE.txt
Requires-Dist: numpy >=1.17
Requires-Dist: scipy >=1.3.1
Requires-Dist: scikit-learn >=0.22
Requires-Dist: numba >=0.51.2
Requires-Dist: pynndescent >=0.5
Requires-Dist: tqdm
Provides-Extra: parametric_umap
Requires-Dist: tensorflow >=2.1 ; extra == 'parametric_umap'
Provides-Extra: plot
Requires-Dist: pandas ; extra == 'plot'
Requires-Dist: matplotlib ; extra == 'plot'
Requires-Dist: datashader ; extra == 'plot'
Requires-Dist: bokeh ; extra == 'plot'
Requires-Dist: holoviews ; extra == 'plot'
Requires-Dist: colorcet ; extra == 'plot'
Requires-Dist: seaborn ; extra == 'plot'
Requires-Dist: scikit-image ; extra == 'plot'
Provides-Extra: tbb
Requires-Dist: tbb >=2019.0 ; extra == 'tbb'
